MANIFEST.in
readme.rst
setup.cfg
setup.py
pythonish_validator/__init__.py
pythonish_validator/basic.py
pythonish_validator/common.py
pythonish_validator.egg-info/PKG-INFO
pythonish_validator.egg-info/SOURCES.txt
pythonish_validator.egg-info/dependency_links.txt
pythonish_validator.egg-info/not-zip-safe
pythonish_validator.egg-info/top_level.txt
test/test_check_chain.py
test/test_custom_validation.py
test/test_object.py
test/test_re_compile.py
test/test_repr.py
test/test_required.py
test/test_simple.py
test/test_simplest.py
test/test_typing_composite.py
test/test_union.py
test/test_validate.py