Metadata-Version: 1.1
Name: pythonish-validator
Version: 0.5.1
Summary: Pythonish object scheme validator
Home-page: https://github.com/bugov/pythonish-validator
Author: Georgy Bazhukov
Author-email: georgy.bazhukov@gmail.com
License: BSD
Keywords: validator data check structure scheme
Platform: UNKNOWN
Classifier: Intended Audience :: Developers
Classifier: License :: OSI Approved :: BSD License
Classifier: Programming Language :: Python
Classifier: Programming Language :: Python :: 3
Classifier: Programming Language :: Python :: 3.7
Classifier: Programming Language :: Python :: 3.8
